{
  "name": {
    "en": "Social Insurance Institution of Finland",
    "fi": "Kela"
  },
  "registers": [
    {
      "name": {
        "en": "Benefits Register",
        "fi": "=HYPERLINK(\"https://www.kela.fi/documents/10180/7276260/Tietosuojaseloste+-+Etuusrekisteri..pdf/\",\"Etuusrekisteri\")"
      },
      "isHarmonized": false,
      "link": {
        "fi": "",
        "en": ""
      },
      "registerDetails": [
        {
          "name": {
            "en": "Psychotropic medicines",
            "fi": "Lääkärin määräämät psyykenlääkkeet"
          },
          "note": {
            "en": "",
            "fi": ""
          },
          "samplings": [
            {
              "startDate": "1994-01-01",
              "endDate": "2016-12-31",
              "cohort": "1987",
              "category": {
                "fi": "kohorttilaiset",
                "en": "subjects"
              }
            },
            {
              "startDate": "1997-01-01",
              "endDate": "2016-12-31",
              "cohort": "1997",
              "category": {
                "fi": "kohorttilaiset",
                "en": "subjects"
              }
            }
          ]
        },
        {
          "name": {
            "en": "Special reimpbursement rights",
            "fi": "Erityiskorvausoikeudet"
          },
          "note": {
            "en": "",
            "fi": ""
          },
          "samplings": [
            {
              "startDate": "1987-01-01",
              "endDate": "2012-12-31",
              "cohort": "1987",
              "category": {
                "fi": "kohorttilaiset",
                "en": "subjects"
              }
            }
          ]
        },
        {
          "name": {
            "en": "Child home care allowance",
            "fi": "Lastenhoitotuki"
          },
          "note": {
            "en": "",
            "fi": ""
          },
          "samplings": [
            {
              "startDate": "1987-01-01",
              "endDate": "2003-12-31",
              "cohort": "1987",
              "category": {
                "fi": "kohorttilaiset",
                "en": "subjects"
              }
            }
          ]
        },
        {
          "name": {
            "en": "Disability benefits",
            "fi": "Vammaistuet"
          },
          "note": {
            "en": "",
            "fi": ""
          },
          "samplings": [
            {
              "startDate": "1987-01-01",
              "endDate": "2016-12-31",
              "cohort": "1987",
              "category": {
                "fi": "kohorttilaiset",
                "en": "subjects"
              }
            },
            {
              "startDate": "1997-01-01",
              "endDate": "2016-12-31",
              "cohort": "1997",
              "category": {
                "fi": "kohorttilaiset",
                "en": "subjects"
              }
            }
          ]
        },
        {
          "name": {
            "en": "Parental allowance",
            "fi": "Äitiys-, isyys- ja vanhempainpäiväraha"
          },
          "note": {
            "en": "",
            "fi": ""
          },
          "samplings": [
            {
              "startDate": "1987-01-01",
              "endDate": "2016-12-31",
              "cohort": "1987",
              "category": {
                "fi": "kohorttilaiset",
                "en": "subjects"
              }
            },
            {
              "startDate": "1997-01-01",
              "endDate": "2016-12-31",
              "cohort": "1997",
              "category": {
                "fi": "kohorttilaiset",
                "en": "subjects"
              }
            },
            {
              "startDate": "1986-01-01",
              "endDate": "1994-12-31",
              "cohort": "1987",
              "category": {
                "fi": "vanhemmat",
                "en": "parents"
              }
            },
            {
              "startDate": "1997-01-01",
              "endDate": "2016-12-31",
              "cohort": "1997",
              "category": {
                "fi": "vanhemmat",
                "en": "parents"
              }
            }
          ]
        },
        {
          "name": {
            "en": "Home care allowance",
            "fi": "Kotihoidontuki"
          },
          "note": {
            "en": "",
            "fi": ""
          },
          "samplings": [
            {
              "startDate": "1987-01-01",
              "endDate": "2016-12-31",
              "cohort": "1987",
              "category": {
                "fi": "kohorttilaiset",
                "en": "subjects"
              }
            },
            {
              "startDate": "1997-01-01",
              "endDate": "2016-12-31",
              "cohort": "1997",
              "category": {
                "fi": "kohorttilaiset",
                "en": "subjects"
              }
            }
          ]
        },
        {
          "name": {
            "en": "Unemployment benefits",
            "fi": "Työttömyyskorvaustiedot"
          },
          "note": {
            "en": "",
            "fi": ""
          },
          "samplings": [
            {
              "startDate": "2005-01-01",
              "endDate": "2012-12-31",
              "cohort": "1987",
              "category": {
                "fi": "kohorttilaiset",
                "en": "subjects"
              }
            },
            {
              "startDate": "1987-01-01",
              "endDate": "2016-12-31",
              "cohort": "1987",
              "category": {
                "fi": "vanhemmat",
                "en": "parents"
              }
            },
            {
              "startDate": "1997-01-01",
              "endDate": "2016-12-31",
              "cohort": "1997",
              "category": {
                "fi": "vanhemmat",
                "en": "parents"
              }
            }
          ]
        },
        {
          "name": {
            "en": "Basic unemployment allowance",
            "fi": "Peruspäiväraha"
          },
          "note": {
            "en": "",
            "fi": ""
          },
          "samplings": [
            {
              "startDate": "1987-01-01",
              "endDate": "2016-12-31",
              "cohort": "1987",
              "category": {
                "fi": "kohorttilaiset",
                "en": "subjects"
              }
            },
            {
              "startDate": "1997-01-01",
              "endDate": "2016-12-31",
              "cohort": "1997",
              "category": {
                "fi": "kohorttilaiset",
                "en": "subjects"
              }
            }
          ]
        },
        {
          "name": {
            "en": "Labour market subsidy",
            "fi": "Työmarkkinatuki"
          },
          "note": {
            "en": "",
            "fi": ""
          },
          "samplings": [
            {
              "startDate": "1994-01-01",
              "endDate": "2016-12-31",
              "cohort": "1987",
              "category": {
                "fi": "kohorttilaiset",
                "en": "subjects"
              }
            },
            {
              "startDate": "1997-01-01",
              "endDate": "2016-12-31",
              "cohort": "1997",
              "category": {
                "fi": "kohorttilaiset",
                "en": "subjects"
              }
            }
          ]
        },
        {
          "name": {
            "en": "Rehabilitation allowance",
            "fi": "Kuntoutusraha"
          },
          "note": {
            "en": "",
            "fi": ""
          },
          "samplings": [
            {
              "startDate": "2003-01-01",
              "endDate": "2016-12-31",
              "cohort": "1987",
              "category": {
                "fi": "kohorttilaiset",
                "en": "subjects"
              }
            },
            {
              "startDate": "2013-01-01",
              "endDate": "2016-12-31",
              "cohort": "1997",
              "category": {
                "fi": "kohorttilaiset",
                "en": "subjects"
              }
            }
          ]
        },
        {
          "name": {
            "en": "Rehabilitations",
            "fi": "Kuntoutukset"
          },
          "note": {
            "en": "",
            "fi": ""
          },
          "samplings": [
            {
              "startDate": "1987-01-01",
              "endDate": "2016-12-31",
              "cohort": "1987",
              "category": {
                "fi": "kohorttilaiset",
                "en": "subjects"
              }
            },
            {
              "startDate": "1997-01-01",
              "endDate": "2016-12-31",
              "cohort": "1997",
              "category": {
                "fi": "kohorttilaiset",
                "en": "subjects"
              }
            }
          ]
        },
        {
          "name": {
            "en": "Disability pension",
            "fi": "Työkyvyttömyyseläkkeet"
          },
          "note": {
            "en": "",
            "fi": ""
          },
          "samplings": [
            {
              "startDate": "2003-01-01",
              "endDate": "2016-12-31",
              "cohort": "1987",
              "category": {
                "fi": "kohorttilaiset",
                "en": "subjects"
              }
            },
            {
              "startDate": "2013-01-01",
              "endDate": "2016-12-31",
              "cohort": "1997",
              "category": {
                "fi": "kohorttilaiset",
                "en": "subjects"
              }
            }
          ]
        },
        {
          "name": {
            "en": "Study gnats",
            "fi": "Opintotuki"
          },
          "note": {
            "en": "",
            "fi": ""
          },
          "samplings": [
            {
              "startDate": "1987-01-01",
              "endDate": "2016-12-31",
              "cohort": "1987",
              "category": {
                "fi": "kohorttilaiset",
                "en": "subjects"
              }
            },
            {
              "startDate": "1997-01-01",
              "endDate": "2016-12-31",
              "cohort": "1997",
              "category": {
                "fi": "kohorttilaiset",
                "en": "subjects"
              }
            }
          ]
        },
        {
          "name": {
            "en": "Marital status, county, municipality",
            "fi": "Siviilisääty, lääni, kunta"
          },
          "note": {
            "en": "",
            "fi": ""
          },
          "samplings": [
            {
              "startDate": "1988-01-01",
              "endDate": "1994-12-31",
              "cohort": "1987",
              "category": {
                "fi": "vanhemmat",
                "en": "parents"
              }
            }
          ]
        },
        {
          "name": {
            "en": "Parents' all children",
            "fi": "Vanhempien kaikki lapset"
          },
          "note": {
            "en": "",
            "fi": ""
          },
          "samplings": [
            {
              "startDate": "1939-01-01",
              "endDate": "2013-12-31",
              "cohort": "1987",
              "category": {
                "fi": "vanhemmat",
                "en": "parents"
              }
            }
          ]
        },
        {
          "name": {
            "en": "Private doctor visits",
            "fi": "Yksityiset lääkärissäkäynnit"
          },
          "note": {
            "en": "",
            "fi": ""
          },
          "samplings": [
            {
              "startDate": "1996-01-01",
              "endDate": "2012-12-31",
              "cohort": "1987",
              "category": {
                "fi": "kohorttilaiset",
                "en": "subjects"
              }
            }
          ]
        }
      ]
    }
  ]
}